[
    {
        "_id": "1",
        "source": "",
        "title": "Как Найти и Купить Билеты по Евросоюзу: Полезные Советы и Источники",
        "h1": "Как Найти и Купить Билеты по Евросоюзу",
        "h2": "Путешествие по Евросоюзу — это увлекательное приключение, но выбор и покупка билетов могут быть немного ошеломляющими. В этой статье мы предоставим вам полезные советы и расскажем о некоторых источниках, которые помогут вам найти и приобрести билеты по Евросоюзу с легкостью.",
        "h3": "",
        "category": "travel",
        "description": "",
        "content":{
          "article":[
            {
              "title": "1. FlixBus",
              "a": "https://global.flixbus.com/",
              "image":"",      
              "content": "FlixBus - это один из популярных способов путешествия по Европе. Они предоставляют широкий выбор автобусных маршрутов по всему Евросоюзу. С их удобным веб-сайтом и мобильным приложением вы можете легко искать и бронировать билеты. Не забудьте проверить их акции и скидки для экономии денег."
            },
            {
                "title": "2. Polrail",
                "a": "https://booking.polrail.com/index.php?main_page=page_5",
                "image":"",      
                "content": "Если вы планируете путешествовать по Польше и соседним странам, Polrail может быть вашим надежным источником для заказа билетов на поезда. Их веб-сайт предлагает простой способ поиска маршрутов и бронирования билетов на поезд."
              },
              {
                "title": "3. Omio",
                "a": "https://www.omio.ru/",
                "image":"",      
                "content": "Omio (ранее GoEuro) — это отличный ресурс для сравнения и заказа билетов на поезда, автобусы и другие виды транспорта в Евросоюзе. Их платформа позволяет вам сравнивать цены и времена в путешествиях между разными городами и странами, чтобы выбрать наиболее подходящий вариант."
              },
              {
                "title": "Заключение:",
                "a": "",
                "image":"",      
                "content": "Путешествие по Евросоюзу может стать незабываемым опытом, и правильный выбор билетов сделает его еще более удивительным. Независимо от того, путешествуете ли вы на автобусе, поезде или другом виде транспорта, вы всегда можете воспользоваться указанными источниками для поиска и бронирования билетов. Путешествуйте без хлопот и наслаждайтесь своими приключениями в Евросоюзе!"
              }
            
          ]
        } ,
        "image": "/images/news/flixbus.webp"
      },
      {
        "_id": "2",
        "source": "",
        "title": "11111Как Найти и Купить Билеты по Евросоюзу: Полезные Советы и Источники",
        "h1": "Как Найти и Купить Билеты по Евросоюзу",
        "h2": "Путешествие по Евросоюзу — это увлекательное приключение, но выбор и покупка билетов могут быть немного ошеломляющими. В этой статье мы предоставим вам полезные советы и расскажем о некоторых источниках, которые помогут вам найти и приобрести билеты по Евросоюзу с легкостью.",
        "h3": "",
        "category": "travel",
        "description": "",
        "content":{
          "article":[
            {
              "title": "1. FlixBus",
              "a": "https://global.flixbus.com/",
              "image":"",      
              "content": "FlixBus - это один из популярных способов путешествия по Европе. Они предоставляют широкий выбор автобусных маршрутов по всему Евросоюзу. С их удобным веб-сайтом и мобильным приложением вы можете легко искать и бронировать билеты. Не забудьте проверить их акции и скидки для экономии денег."
            },
            {
                "title": "2. Polrail",
                "a": "https://booking.polrail.com/index.php?main_page=page_5",
                "image":"",      
                "content": "Если вы планируете путешествовать по Польше и соседним странам, Polrail может быть вашим надежным источником для заказа билетов на поезда. Их веб-сайт предлагает простой способ поиска маршрутов и бронирования билетов на поезд."
              },
              {
                "title": "3. Omio",
                "a": "https://www.omio.ru/",
                "image":"",      
                "content": "Omio (ранее GoEuro) — это отличный ресурс для сравнения и заказа билетов на поезда, автобусы и другие виды транспорта в Евросоюзе. Их платформа позволяет вам сравнивать цены и времена в путешествиях между разными городами и странами, чтобы выбрать наиболее подходящий вариант."
              },
              {
                "title": "Заключение:",
                "a": "",
                "image":"",      
                "content": "Путешествие по Евросоюзу может стать незабываемым опытом, и правильный выбор билетов сделает его еще более удивительным. Независимо от того, путешествуете ли вы на автобусе, поезде или другом виде транспорта, вы всегда можете воспользоваться указанными источниками для поиска и бронирования билетов. Путешествуйте без хлопот и наслаждайтесь своими приключениями в Евросоюзе!"
              }
            
          ]
        } ,
        "image": "/images/news/flixbus.webp"
      },
      {
        "_id": "3",
        "source": "",
        "title": "11111Как Найти и Купить Билеты по Евросоюзу: Полезные Советы и Источники",
        "h1": "Как Найти и Купить Билеты по Евросоюзу",
        "h2": "Путешествие по Евросоюзу — это увлекательное приключение, но выбор и покупка билетов могут быть немного ошеломляющими. В этой статье мы предоставим вам полезные советы и расскажем о некоторых источниках, которые помогут вам найти и приобрести билеты по Евросоюзу с легкостью.",
        "h3": "",
        "category": "travel",
        "description": "",
        "content":{
          "article":[
            {
              "title": "1. FlixBus",
              "a": "https://global.flixbus.com/",
              "image":"",      
              "content": "FlixBus - это один из популярных способов путешествия по Европе. Они предоставляют широкий выбор автобусных маршрутов по всему Евросоюзу. С их удобным веб-сайтом и мобильным приложением вы можете легко искать и бронировать билеты. Не забудьте проверить их акции и скидки для экономии денег."
            },
            {
                "title": "2. Polrail",
                "a": "https://booking.polrail.com/index.php?main_page=page_5",
                "image":"",      
                "content": "Если вы планируете путешествовать по Польше и соседним странам, Polrail может быть вашим надежным источником для заказа билетов на поезда. Их веб-сайт предлагает простой способ поиска маршрутов и бронирования билетов на поезд."
              },
              {
                "title": "3. Omio",
                "a": "https://www.omio.ru/",
                "image":"",      
                "content": "Omio (ранее GoEuro) — это отличный ресурс для сравнения и заказа билетов на поезда, автобусы и другие виды транспорта в Евросоюзе. Их платформа позволяет вам сравнивать цены и времена в путешествиях между разными городами и странами, чтобы выбрать наиболее подходящий вариант."
              },
              {
                "title": "Заключение:",
                "a": "",
                "image":"",      
                "content": "Путешествие по Евросоюзу может стать незабываемым опытом, и правильный выбор билетов сделает его еще более удивительным. Независимо от того, путешествуете ли вы на автобусе, поезде или другом виде транспорта, вы всегда можете воспользоваться указанными источниками для поиска и бронирования билетов. Путешествуйте без хлопот и наслаждайтесь своими приключениями в Евросоюзе!"
              }
            
          ]
        } ,
        "image": "/images/news/flixbus.webp"
      },
      {
        "_id": "4",
        "source": "",
        "title": "11111Как Найти и Купить Билеты по Евросоюзу: Полезные Советы и Источники",
        "h1": "Как Найти и Купить Билеты по Евросоюзу",
        "h2": "Путешествие по Евросоюзу — это увлекательное приключение, но выбор и покупка билетов могут быть немного ошеломляющими. В этой статье мы предоставим вам полезные советы и расскажем о некоторых источниках, которые помогут вам найти и приобрести билеты по Евросоюзу с легкостью.",
        "h3": "",
        "category": "travel",
        "description": "",
        "content":{
          "article":[
            {
              "title": "1. FlixBus",
              "a": "https://global.flixbus.com/",
              "image":"",      
              "content": "FlixBus - это один из популярных способов путешествия по Европе. Они предоставляют широкий выбор автобусных маршрутов по всему Евросоюзу. С их удобным веб-сайтом и мобильным приложением вы можете легко искать и бронировать билеты. Не забудьте проверить их акции и скидки для экономии денег."
            },
            {
                "title": "2. Polrail",
                "a": "https://booking.polrail.com/index.php?main_page=page_5",
                "image":"",      
                "content": "Если вы планируете путешествовать по Польше и соседним странам, Polrail может быть вашим надежным источником для заказа билетов на поезда. Их веб-сайт предлагает простой способ поиска маршрутов и бронирования билетов на поезд."
              },
              {
                "title": "3. Omio",
                "a": "https://www.omio.ru/",
                "image":"",      
                "content": "Omio (ранее GoEuro) — это отличный ресурс для сравнения и заказа билетов на поезда, автобусы и другие виды транспорта в Евросоюзе. Их платформа позволяет вам сравнивать цены и времена в путешествиях между разными городами и странами, чтобы выбрать наиболее подходящий вариант."
              },
              {
                "title": "Заключение:",
                "a": "",
                "image":"",      
                "content": "Путешествие по Евросоюзу может стать незабываемым опытом, и правильный выбор билетов сделает его еще более удивительным. Независимо от того, путешествуете ли вы на автобусе, поезде или другом виде транспорта, вы всегда можете воспользоваться указанными источниками для поиска и бронирования билетов. Путешествуйте без хлопот и наслаждайтесь своими приключениями в Евросоюзе!"
              }
            
          ]
        } ,
        "image": "/images/news/flixbus.webp"
      },
      {
        "_id": "5",
        "source": "",
        "title": "11111Как Найти и Купить Билеты по Евросоюзу: Полезные Советы и Источники",
        "h1": "Как Найти и Купить Билеты по Евросоюзу",
        "h2": "Путешествие по Евросоюзу — это увлекательное приключение, но выбор и покупка билетов могут быть немного ошеломляющими. В этой статье мы предоставим вам полезные советы и расскажем о некоторых источниках, которые помогут вам найти и приобрести билеты по Евросоюзу с легкостью.",
        "h3": "",
        "category": "travel",
        "description": "",
        "content":{
          "article":[
            {
              "title": "1. FlixBus",
              "a": "https://global.flixbus.com/",
              "image":"",      
              "content": "FlixBus - это один из популярных способов путешествия по Европе. Они предоставляют широкий выбор автобусных маршрутов по всему Евросоюзу. С их удобным веб-сайтом и мобильным приложением вы можете легко искать и бронировать билеты. Не забудьте проверить их акции и скидки для экономии денег."
            },
            {
                "title": "2. Polrail",
                "a": "https://booking.polrail.com/index.php?main_page=page_5",
                "image":"",      
                "content": "Если вы планируете путешествовать по Польше и соседним странам, Polrail может быть вашим надежным источником для заказа билетов на поезда. Их веб-сайт предлагает простой способ поиска маршрутов и бронирования билетов на поезд."
              },
              {
                "title": "3. Omio",
                "a": "https://www.omio.ru/",
                "image":"",      
                "content": "Omio (ранее GoEuro) — это отличный ресурс для сравнения и заказа билетов на поезда, автобусы и другие виды транспорта в Евросоюзе. Их платформа позволяет вам сравнивать цены и времена в путешествиях между разными городами и странами, чтобы выбрать наиболее подходящий вариант."
              },
              {
                "title": "Заключение:",
                "a": "",
                "image":"",      
                "content": "Путешествие по Евросоюзу может стать незабываемым опытом, и правильный выбор билетов сделает его еще более удивительным. Независимо от того, путешествуете ли вы на автобусе, поезде или другом виде транспорта, вы всегда можете воспользоваться указанными источниками для поиска и бронирования билетов. Путешествуйте без хлопот и наслаждайтесь своими приключениями в Евросоюзе!"
              }
            
          ]
        } ,
        "image": "/images/news/flixbus.webp"
      }
]